env/bin/approxmc.py
env/bin/fm.py
env/bin/genhard.py
env/bin/lbx.py
env/bin/lsu.py
env/bin/mcsls.py
env/bin/models.py
env/bin/musx.py
env/bin/optux.py
env/bin/rc2.py
fmfactlabel/__init__.py
fmfactlabel/characterization.py
fmfactlabel/constraints_utils.py
fmfactlabel/fm_analysis.py
fmfactlabel/fm_metadata.py
fmfactlabel/fm_metrics.py
fmfactlabel/fm_properties.py
fmfactlabel/fm_utils.py
web/flask_app.py
fmfactlabel-1.8.1.dist-info/METADATA
fmfactlabel-1.8.1.dist-info/WHEEL
fmfactlabel-1.8.1.dist-info/top_level.txt
fmfactlabel-1.8.1.dist-info/RECORD
