Metadata-Version: 2.4
Name: fmfactlabel
Version: 1.8.1
Summary: FM Fact Label backend to characterize feature models.
Author: José A. Galindo, Ángela Pérez de Guzmán de Miguel, Mónica Pinto, Lidia Fuentes, David Benavides
Author-email: José Miguel Horcas <horcas@uma.es>
License-Expression: GPL-3.0-or-later
Project-URL: Homepage, https://fmfactlabel.github.io/
Project-URL: GitHub, https://github.com/fmfactlabel/fm_characterization
Classifier: Programming Language :: Python :: 3
Classifier: Operating System :: OS Independent
Requires-Python: >=3.11
Requires-Dist: flamapy-fw~=2.1.0.dev0
Requires-Dist: flamapy-fm~=2.1.0.dev0
Requires-Dist: flamapy-sat~=2.1.0.dev0
Requires-Dist: flamapy-bdd~=2.1.0.dev0
